LICENSE.txt
README.md
beancount_ce/__init__.py
beancount_ce/extract_statement.py
beancount_ce/importer_csv.py
beancount_ce/importer_pdf.py
beancount_ce/regex_formatter.py
beancount_ce-1.2.0.dist-info/LICENSE.txt
beancount_ce-1.2.0.dist-info/METADATA
beancount_ce-1.2.0.dist-info/WHEEL
beancount_ce-1.2.0.dist-info/RECORD
