Metadata-Version: 2.1
Name: beancount-ce
Version: 1.2.0
Summary: Beancount statements (pdf and csv) importer for Caisse d'Epargne bank
Home-page: https://github.com/ArthurFDLR/beancount-ce
License: MIT
Keywords: banking,beancount,cli-accounting,finance
Author: Arthur Findelair
Author-email: arthfind@gmail.com
Requires-Python: >=3.6,<4.0
Classifier: Development Status :: 5 - Production/Stable
Classifier: Environment :: Plugins
Classifier: Intended Audience :: End Users/Desktop
Classifier: Intended Audience :: Financial and Insurance Industry
Classifier: License :: OSI Approved :: MIT License
Classifier: Programming Language :: Python :: 3
Classifier: Programming Language :: Python :: 3.6
Classifier: Programming Language :: Python :: 3.7
Classifier: Programming Language :: Python :: 3.8
Classifier: Programming Language :: Python :: 3.9
Classifier: Programming Language :: Python :: 3.10
Classifier: Programming Language :: Python :: 3.11
Classifier: Programming Language :: Python :: 3.12
Classifier: Programming Language :: Python :: 3 :: Only
Requires-Dist: beancount (>=2.2,<3.0)
Requires-Dist: pdfminer.six (>=20200726,<20200727)
Requires-Dist: regex (>=2020.7.14,<2021.0.0)
Project-URL: Repository, https://github.com/ArthurFDLR/beancount-ce
